truffleHog/__init__.py
truffleHog/regexes.json
truffleHog/truffleHog.py
truffleHog/whitelist.py
truffleHog/whitelistExamples.py
MechTruffleHog-1.1.0.dist-info/LICENSE
MechTruffleHog-1.1.0.dist-info/METADATA
MechTruffleHog-1.1.0.dist-info/WHEEL
MechTruffleHog-1.1.0.dist-info/entry_points.txt
MechTruffleHog-1.1.0.dist-info/top_level.txt
MechTruffleHog-1.1.0.dist-info/RECORD
